walacor_python_sdk-0.1.6.dist-info/licenses/LICENSE
walacor_sdk/__init__.py
walacor_sdk/py.typed
walacor_sdk/authentication/__init__.py
walacor_sdk/authentication/auth_service.py
walacor_sdk/authentication/models/__init__.py
walacor_sdk/base/__init__.py
walacor_sdk/base/base_service.py
walacor_sdk/base/facade.py
walacor_sdk/base/w_client.py
walacor_sdk/base/walacor_service.py
walacor_sdk/base/model/__init__.py
walacor_sdk/base/model/base_response_model.py
walacor_sdk/data_requests/__init__.py
walacor_sdk/data_requests/data_requests_service.py
walacor_sdk/data_requests/models/__init__.py
walacor_sdk/data_requests/models/data_request_response.py
walacor_sdk/data_requests/models/data_requests_request.py
walacor_sdk/data_requests/models/models.py
walacor_sdk/file_request/__init__.py
walacor_sdk/file_request/file_request_service.py
walacor_sdk/file_request/models/__init__.py
walacor_sdk/file_request/models/file_request_request.py
walacor_sdk/file_request/models/file_request_response.py
walacor_sdk/file_request/models/models.py
walacor_sdk/schema/__init__.py
walacor_sdk/schema/schema_service.py
walacor_sdk/schema/models/__init__.py
walacor_sdk/schema/models/models.py
walacor_sdk/schema/models/schema_request.py
walacor_sdk/schema/models/schema_response.py
walacor_sdk/utils/__init__
walacor_sdk/utils/enums.py
walacor_sdk/utils/exceptions.py
walacor_sdk/utils/global_exception_handler.py
walacor_sdk/utils/logger.py
walacor_python_sdk-0.1.6.dist-info/METADATA
walacor_python_sdk-0.1.6.dist-info/WHEEL
walacor_python_sdk-0.1.6.dist-info/top_level.txt
walacor_python_sdk-0.1.6.dist-info/RECORD
