Metadata-Version: 2.4
Name: walacor_python_sdk
Version: 0.1.6
Summary: Python SDK for Walacor
Author-email: Garo Kechichian <garo.keshish@gmail.com>
License: Apache-2.0
Project-URL: Documentation, https://apidoc.walacor.com
Project-URL: Homepage, https://www.walacor.com
Keywords: data-transformations,lineage,provenance,walacor
Classifier: Development Status :: 4 - Beta
Classifier: Intended Audience :: Developers
Classifier: License :: OSI Approved :: Apache Software License
Classifier: Programming Language :: Python :: 3 :: Only
Classifier: Programming Language :: Python :: 3.11
Classifier: Programming Language :: Python :: 3.12
Classifier: Programming Language :: Python :: 3.13
Requires-Python: >=3.11
License-File: LICENSE
Requires-Dist: requests>=2.32.3
Requires-Dist: pydantic>=2.10
Provides-Extra: test
Requires-Dist: pytest>=6; extra == "test"
Provides-Extra: dev
Requires-Dist: pre-commit; extra == "dev"
Requires-Dist: tox; extra == "dev"
Provides-Extra: data-science
Requires-Dist: pandas>=2.0; extra == "data-science"
Requires-Dist: pyarrow>=14; extra == "data-science"
Requires-Dist: numpy>=1.26; extra == "data-science"
Dynamic: license-file
